freud/__init__.py
freud/__main__.py
freud/key_bindings.py
freud/utils.py
freud/api/__init__.py
freud/api/request.py
freud/api/response.py
freud/model/__init__.py
freud/server_control/__init__.py
freud/server_control/auth_dialog.py
freud/server_control/call_editor.py
freud/server_control/delete_server.py
freud/server_control/headers_dialog.py
freud/server_control/server_dialog.py
freud/ui/__init__.py
freud/ui/body_container.py
freud/ui/dialog.py
freud/ui/keys.py
freud/ui/root_container.py
freud/ui/server_container.py
freud/ui/sort.py
freud/ui/style.py
freud/ui/text_buffers.py
freud-0.1.2.dist-info/METADATA
freud-0.1.2.dist-info/RECORD
freud-0.1.2.dist-info/WHEEL
freud-0.1.2.dist-info/entry_points.txt
freud-0.1.2.dist-info/top_level.txt
tests/__init__.py
tests/conftest.py
tests/test_database.py
tests/test_layout.py
tests/test_requests.py
tests/utils.py
