Metadata-Version: 2.1
Name: freud
Version: 0.1.2
Summary: TUI REST client to analyze API endpoints
Home-page: https://github.com/stloma/freud
Author: Stephen Martin
Author-email: lockwood@opperline.com
License: UNKNOWN
Project-URL: Bug Reports, https://github.com/stloma/freud/issues
Project-URL: Source, https://github.com/stloma/freud
Keywords: cli tui http rest request api
Platform: UNKNOWN
Classifier: Development Status :: 3 - Alpha
Classifier: Intended Audience :: Developers
Classifier: Topic :: Software Development :: Build Tools
Classifier: License :: OSI Approved :: MIT License
Classifier: Programming Language :: Python :: 3.5
Classifier: Programming Language :: Python :: 3.6
Provides-Extra: dev
Requires-Dist: requests
Requires-Dist: prompt-toolkit (==2.0.3)
Requires-Dist: pygments
Provides-Extra: dev
Requires-Dist: flake8; extra == 'dev'
Requires-Dist: pytest; extra == 'dev'
Requires-Dist: pytest-asyncio; extra == 'dev'
Requires-Dist: pytest-httpbin; extra == 'dev'
Requires-Dist: tox; extra == 'dev'
